sphericalmercator.py
sphericalmercator-0.0.4.dist-info/DESCRIPTION.rst
sphericalmercator-0.0.4.dist-info/METADATA
sphericalmercator-0.0.4.dist-info/RECORD
sphericalmercator-0.0.4.dist-info/WHEEL
sphericalmercator-0.0.4.dist-info/metadata.json
sphericalmercator-0.0.4.dist-info/top_level.txt
