Metadata-Version: 2.0
Name: sphericalmercator
Version: 0.0.4
Summary: Tool for calculate XYZ-tile bounding box in geodesic coordinates
Home-page: https://bitbucket.org/lighter/spherical-mercator/
Author: UNKNOWN
Author-email: UNKNOWN
License: UNKNOWN
Platform: UNKNOWN
